pywheelhouse/__init__.py
pywheelhouse/__main__.py
pywheelhouse/cli.py
pywheelhouse/core.py
pywheelhouse/docs/CHANGELOG.md
pywheelhouse/docs/CLI.md
pywheelhouse/docs/CONFIG.md
pywheelhouse/docs/EXAMPLES.md
pywheelhouse/docs/FAQ.md
pywheelhouse/docs/LIMITATIONS.md
pywheelhouse/docs/PYTHON.md
pywheelhouse/docs/README.md
pywheelhouse/docs/SECURITY.md
pywheelhouse/docs/TROUBLESHOOTING.md
pywheelhouse/docs/WORKFLOWS.md
pywheelhouse/docs/__init__.py
pywheelhouse/docs/__main__.py
pywheelhouse-0.0.0.dist-info/licenses/LICENSE
pywheelhouse-0.0.0.dist-info/METADATA
pywheelhouse-0.0.0.dist-info/WHEEL
pywheelhouse-0.0.0.dist-info/entry_points.txt
pywheelhouse-0.0.0.dist-info/top_level.txt
pywheelhouse-0.0.0.dist-info/RECORD
